source_code/.gitignore
source_code/.gitkeep
source_code/config.yaml
source_code/example.config.yaml
source_code/main.py
source_code/requirements.txt
source_code/templates/javascript/nest/Dockerfile/Dockerfile.j2
source_code/templates/javascript/nest/Engine/engine.Dockerfile
source_code/templates/python/django_template/Databases/mariadb/.env.j2
source_code/templates/python/django_template/Databases/mariadb/docker-compose.yaml.j2
source_code/templates/python/django_template/Databases/mariadb/requirements.txt.j2
source_code/templates/python/django_template/Databases/mariadb/settings.py.j2
source_code/templates/python/django_template/Databases/mysql/.env.j2
source_code/templates/python/django_template/Databases/mysql/docker-compose.yaml.j2
source_code/templates/python/django_template/Databases/mysql/requirement.txt.j2
source_code/templates/python/django_template/Databases/mysql/settings.py.j2
source_code/templates/python/django_template/Databases/oracle/.env.j2
source_code/templates/python/django_template/Databases/oracle/docker-compose.yaml.j2
source_code/templates/python/django_template/Databases/oracle/requirements.txt.j2
source_code/templates/python/django_template/Databases/oracle/settings.py.j2
source_code/templates/python/django_template/Databases/postgresql/.env.j2
source_code/templates/python/django_template/Databases/postgresql/docker-compose.yaml.j2
source_code/templates/python/django_template/Databases/postgresql/requirements.txt.j2
source_code/templates/python/django_template/Databases/postgresql/settings.py.j2
source_code/templates/python/django_template/Databases/sqlite/.env.j2
source_code/templates/python/django_template/Databases/sqlite/docker-compose.yaml.j2
source_code/templates/python/django_template/Databases/sqlite/requirements.txt.j2
source_code/templates/python/django_template/Databases/sqlite/settings.py.j2
source_code/templates/python/django_template/Dockerfile/Dockerfile.j2
source_code/templates/python/django_template/Engine/engine.Dockerfile
stack_builder-0.1.1.dist-info/LICENSE
stack_builder-0.1.1.dist-info/METADATA
stack_builder-0.1.1.dist-info/WHEEL
stack_builder-0.1.1.dist-info/entry_points.txt
stack_builder-0.1.1.dist-info/RECORD
